Workbook

Sheet Project_Overview

Sheet Master_Sheet
A1: Asset Name | B1: Ticker | C1: Region | D1: Asset Type | E1: Currency | F1: Active
A2: Indian Overseas Bank | B2: IOB:NSE | C2: India | D2: Equity | E2: INR | F2: Yes
A3: Nippon India ETF Gold BeES | B3: GOLDBEES:NSE | C3: India | D3: Commodity | E3: INR | F3: Yes
A4: Nippon India Silver ETF | B4: SILVERBEES:NSE | C4: India | D4: Commodity | E4: INR | F4: Yes
A5: Suzlon Energy Ltd | B5: SUZLON:NSE | C5: India | D5: Equity | E5: INR | F5: Yes
A6: Tata Gold Exchange Traded Fund | B6: TATAGOLD:NSE | C6: India | D6: Commodity | E6: INR | F6: Yes
A7: Tata Silver Exchange Traded Fund | B7: TATSILV:NSE | C7: India | D7: Commodity | E7: INR | F7: Yes
A8: Zerodha Gold ETF | B8: GOLDCASE:NSE | C8: India | D8: Commodity | E8: INR | F8: Yes
A9: Zerodha Silver ETF | B9: SILVERCASE:NSE | C9: India | D9: Commodity | E9: INR | F9: Yes
A10: Tesla Inc | B10: TSLA:NASDAQ | C10: US | D10: Equity | E10: USD | F10: Yes
A11: Vanguard Total Stock Market Index Fund ETF | B11: VTI:NYSEARCA | C11: US | D11: ETF | E11: USD | F11: Yes
A12: Invesco QQQ Trust, Series 1 | B12: QQQ:NASDAQ | C12: US | D12: ETF | E12: USD | F12: Yes
... A18: Kotak Silver ETF | B18: SILVER1:NSE | C18: India | D18: ETF | E18: INR | F18: Yes

Sheet IND_TNX
A1: Date | B1: Asset Name | C1: Ticker | D1: Type | E1: Quantity | F1: Trade Value | G1: Trade Price
A2: 45697 | B2: Zerodha Gold ETF | C2: GOLDCASE:NSE | D2: BUY | E2: 5 | F2: =IF(D2="SELL",-E2*G2,E2*G2) -> 83 | G2: 16.6
A3: 23/09/2025 | B3: Zerodha Gold ETF | C3: GOLDCASE:NSE | D3: BUY | E3: 25 | F3: =IF(D3="SELL",-E3*G3,E3*G3) -> 451.75 | G3: 18.07
A4: 23/09/2025 | B4: Tata Silver Exchange Traded Fund | C4: TATSILV:NSE | D4: BUY | E4: 18 | F4: =IF(D4="SELL",-E4*G4,E4*G4) -> 237.24 | G4: 13.18
A5: 23/09/2025 | B5: Zerodha Silver ETF | C5: SILVERCASE:NSE | D5: BUY | E5: 18 | F5: =IF(D5="SELL",-E5*G5,E5*G5) -> 247.32 | G5: 13.74 | J5: s
A6: 23/09/2025 | B6: Zerodha Gold ETF | C6: GOLDCASE:NSE | D6: BUY | E6: 3 | F6: =IF(D6="SELL",-E6*G6,E6*G6) -> 54.21 | G6: 18.07
A7: 15/11/2025 | B7: Tata Silver Exchange Traded Fund | C7: TATSILV:NSE | D7: BUY | E7: 10 | F7: =IF(D7="SELL",-E7*G7,E7*G7) -> 152.1 | G7: 15.21
A8: 15/11/2025 | B8: Zerodha Gold ETF | C8: GOLDCASE:NSE | D8: BUY | E8: 7 | F8: =IF(D8="SELL",-E8*G8,E8*G8) -> 135.59 | G8: 19.37
A9: 15/11/2025 | B9: Zerodha Silver ETF | C9: SILVERCASE:NSE | D9: BUY | E9: 6 | F9: =IF(D9="SELL",-E9*G9,E9*G9) -> 95.1 | G9: 15.85
A10: 46003 | B10: Zerodha Gold ETF | C10: GOLDCASE:NSE | D10: BUY | E10: 2 | F10: =IF(D10="SELL",-E10*G10,E10*G10) -> 40.74 | G10: 20.37
A11: 46003 | B11: Tata Silver Exchange Traded Fund | C11: TATSILV:NSE | D11: BUY | E11: 5 | F11: =IF(D11="SELL",-E11*G11,E11*G11) -> 93.95 | G11: 18.79
A12: 14/12/2025 | B12: Nippon India ETF Gold BeES | C12: GOLDBEES:NSE | D12: BUY | E12: 185 | F12: =IF(D12="SELL",-E12*G12,E12*G12) -> 20366.65 | G12: 110.09
A13: 15/12/2025 | B13: Nippon India Silver ETF | C13: SILVERBEES:NSE | D13: BUY | E13: 55 | F13: =IF(D13="SELL",-E13*G13,E13*G13) -> 9993.5 | G13: 181.7
A14: 15/12/2025 | B14: Nippon India Silver ETF | C14: SILVERBEES:NSE | D14: BUY | E14: 29 | F14: =IF(D14="SELL",-E14*G14,E14*G14) -> 5237.98 | G14: 180.62
A15: 15/12/2025 | B15: Nippon India Silver ETF | C15: SILVERBEES:NSE | D15: BUY | E15: 11 | F15: =IF(D15="SELL",-E15*G15,E15*G15) -> 1983.74 | G15: 180.34
A16: 16/12/2025 | B16: Tata Gold Exchange Traded Fund | C16: TATAGOLD:NSE | D16: BUY | E16: 99 | F16: =IF(D16="SELL",-E16*G16,E16*G16) -> 1285.02 | G16: 12.98
A17: 17/12/2025 | B17: Suzlon Energy Ltd | C17: SUZLON:NSE | D17: BUY | E17: 4 | F17: =IF(D17="SELL",-E17*G17,E17*G17) -> 208.8 | G17: 52.2
A18: 17/12/2025 | B18: Indian Overseas Bank | C18: IOB:NSE | D18: BUY | E18: 8 | F18: =IF(D18="SELL",-E18*G18,E18*G18) -> 281.2 | G18: 35.15
A19: 17/12/2025 | B19: Indian Overseas Bank | C19: IOB:NSE | D19: SELL | E19: 1 | F19: =IF(D19="SELL",-E19*G19,E19*G19) -> -35.14 | G19: 35.14
A20: 17/12/2025 | B20: Suzlon Energy Ltd | C20: SUZLON:NSE | D20: BUY | E20: 1 | F20: =IF(D20="SELL",-E20*G20,E20*G20) -> 52.18 | G20: 52.18
A21: 17/12/2025 | B21: Tata Gold Exchange Traded Fund | C21: TATAGOLD:NSE | D21: BUY | E21: 1 | F21: =IF(D21="SELL",-E21*G21,E21*G21) -> 12.94 | G21: 12.94
A22: 29/12/2025 | B22: Nippon India ETF Gold BeES | C22: GOLDBEES:NSE | D22: BUY | E22: 149 | F22: =IF(D22="SELL",-E22*G22,E22*G22) -> 17149.9 | G22: 115.1
A23: 29/12/2025 | B23: Nippon India Silver ETF | C23: SILVERBEES:NSE | D23: BUY | E23: 100 | F23: =IF(D23="SELL",-E23*G23,E23*G23) -> 23828 | G23: 238.28
... A34: 29/12/2025 | B34: Nippon India Silver ETF | C34: SILVERBEES:NSE | D34: SELL | E34: 90 | F34: =IF(D34="SELL",-E34*G34,E34*G34) -> -20160 | G34: 224

Sheet IND_HOLDINGS
A1: Asset Name | B1: Ticker | C1: Quantity | D1: Avg Price | E1: Invested | F1: Live Price | G1: Current Value | H1: Weight | I1: P&L | J1: Return % | K1: Contribution | M1: Portfolio Totals
A2: {=_xlfn.UNIQUE(IND_TNX[Asset Name])} -> Zerodha Gold ETF | B2: #VALUE! | C2: =SUMIFS(IND_TNX!E:E,IND_TNX!B:B,A2,IND_TNX!D:D,"BUY") -> 42 | D2: =SUMIFS(IND_TNX!F:F,IND_TNX!B:B,A2,IND_TNX!D:D,"BUY") / SUMIFS(IND_TNX!E:E,IND_TNX!B:B,A2,IND_TNX!D:D,"BUY") -> 18.22119 | E2: =C2*D2 -> 765.29 | F2: {=_FV(B2,"Price")} -> 25.27 | G2: =C2*F2 -> 1061.34 | H2: =G2/$N$3 -> 0.0064648162 | I2: =G2-E2 -> 296.05 | J2: =I2/E2 -> 0.38684682 | K2: =H2*J2 -> 0.0025008936 | M2: Total Invested | N2: =SUM(E2:E9) -> 142514.73
A3: Tata Silver Exchange Traded Fund | B3: #VALUE! | C3: =SUMIFS(IND_TNX!E:E,IND_TNX!B:B,A3,IND_TNX!D:D,"BUY") -> 33 | D3: =SUMIFS(IND_TNX!F:F,IND_TNX!B:B,A3,IND_TNX!D:D,"BUY") / SUMIFS(IND_TNX!E:E,IND_TNX!B:B,A3,IND_TNX!D:D,"BUY") -> 14.645152 | E3: =C3*D3 -> 483.29 | F3: {=_FV(B3,"Price")} -> 25.51 | G3: =C3*F3 -> 841.83 | H3: =G3/$N$3 -> 0.0051277406 | I3: =G3-E3 -> 358.54 | J3: =I3/E3 -> 0.74187341 | K3: =H3*J3 -> 0.0038041344 | M3: Total Current Value | N3: =SUM(G2:G9) -> 164171.72
A4: Zerodha Silver ETF | B4: #VALUE! | C4: =SUMIFS(IND_TNX!E:E,IND_TNX!B:B,A4,IND_TNX!D:D,"BUY") -> 24 | D4: =SUMIFS(IND_TNX!F:F,IND_TNX!B:B,A4,IND_TNX!D:D,"BUY") / SUMIFS(IND_TNX!E:E,IND_TNX!B:B,A4,IND_TNX!D:D,"BUY") -> 14.2675 | E4: =C4*D4 -> 342.42 | F4: {=_FV(B4,"Price")} -> 26.7 | G4: =C4*F4 -> 640.8 | H4: =G4/$N$3 -> 0.0039032301 | I4: =G4-E4 -> 298.38 | J4: =I4/E4 -> 0.87138602 | K4: =H4*J4 -> 0.0034012201 | M4: Total P&L | N4: =SUM(I2:I9) -> 21656.99
A5: Nippon India ETF Gold BeES | B5: #VALUE! | C5: =SUMIFS(IND_TNX!E:E,IND_TNX!B:B,A5,IND_TNX!D:D,"BUY") -> 525 | D5: =SUMIFS(IND_TNX!F:F,IND_TNX!B:B,A5,IND_TNX!D:D,"BUY") / SUMIFS(IND_TNX!E:E,IND_TNX!B:B,A5,IND_TNX!D:D,"BUY") -> 113.29404 | E5: =C5*D5 -> 59479.37 | F5: {=_FV(B5,"Price")} -> 132.71 | G5: =C5*F5 -> 69672.75 | H5: =G5/$N$3 -> 0.42438947 | I5: =G5-E5 -> 10193.38 | J5: =I5/E5 -> 0.17137673 | K5: =H5*J5 -> 0.072730481 | M5: Portfolio Return | N5: =N4/N2 -> 0.15196317
A6: Nippon India Silver ETF | B6: #VALUE! | C6: =SUMIFS(IND_TNX!E:E,IND_TNX!B:B,A6,IND_TNX!D:D,"BUY") -> 358 | D6: =SUMIFS(IND_TNX!F:F,IND_TNX!B:B,A6,IND_TNX!D:D,"BUY") / SUMIFS(IND_TNX!E:E,IND_TNX!B:B,A6,IND_TNX!D:D,"BUY") -> 222.35816 | E6: =C6*D6 -> 79604.22 | F6: {=_FV(B6,"Price")} -> 251.69 | G6: =C6*F6 -> 90105.02 | H6: =G6/$N$3 -> 0.54884617 | I6: =G6-E6 -> 10500.8 | J6: =I6/E6 -> 0.1319126 | K6: =H6*J6 -> 0.072399728
A7: Tata Gold Exchange Traded Fund | B7: #VALUE! | C7: =SUMIFS(IND_TNX!E:E,IND_TNX!B:B,A7,IND_TNX!D:D,"BUY") -> 100 | D7: =SUMIFS(IND_TNX!F:F,IND_TNX!B:B,A7,IND_TNX!D:D,"BUY") / SUMIFS(IND_TNX!E:E,IND_TNX!B:B,A7,IND_TNX!D:D,"BUY") -> 12.9796 | E7: =C7*D7 -> 1297.96 | F7: {=_FV(B7,"Price")} -> 15.54 | G7: =C7*F7 -> 1554 | H7: =G7/$N$3 -> 0.0094656985 | I7: =G7-E7 -> 256.04 | J7: =I7/E7 -> 0.1972634 | K7: =H7*J7 -> 0.0018672358
A8: Suzlon Energy Ltd | B8: #VALUE! | C8: =SUMIFS(IND_TNX!E:E,IND_TNX!B:B,A8,IND_TNX!D:D,"BUY") -> 5 | D8: =SUMIFS(IND_TNX!F:F,IND_TNX!B:B,A8,IND_TNX!D:D,"BUY") / SUMIFS(IND_TNX!E:E,IND_TNX!B:B,A8,IND_TNX!D:D,"BUY") -> 52.196 | E8: =C8*D8 -> 260.98 | F8: {=_FV(B8,"Previous close",TRUE)} -> 5.5 | G8: =C8*F8 -> 27.5 | H8: =G8/$N$3 -> 0.00016750753 | I8: =G8-E8 -> -233.48 | J8: =I8/E8 -> -0.89462794 | K8: =H8*J8 -> -0.00014985692
A9: Indian Overseas Bank | B9: #VALUE! | C9: =SUMIFS(IND_TNX!E:E,IND_TNX!B:B,A9,IND_TNX!D:D,"BUY") -> 8 | D9: =SUMIFS(IND_TNX!F:F,IND_TNX!B:B,A9,IND_TNX!D:D,"BUY") / SUMIFS(IND_TNX!E:E,IND_TNX!B:B,A9,IND_TNX!D:D,"BUY") -> 35.15 | E9: =C9*D9 -> 281.2 | F9: {=_FV(B9,"Price")} -> 33.56 | G9: =C9*F9 -> 268.48 | H9: =G9/$N$3 -> 0.0016353608 | I9: =G9-E9 -> -12.72 | J9: =I9/E9 -> -0.045234708 | K9: =H9*J9 -> -7.397507e-05
A10: 0

Sheet SUMMARY
A1: PORTFOLIO DASHBOARD | D1: Metric | E1: Asset | F1: Value
D2: 🥇Top Holding | E2: =INDEX(IND_HOLDINGS!A2:A20, MATCH(MAX(IND_HOLDINGS!H2:H20), IND_HOLDINGS!H2:H20, 0)) -> Nippon India Silver ETF | F2: =MAX(IND_HOLDINGS!H2:H20) -> 0.54884617
A3: Total Invested | B3: =SUM(IND_HOLDINGS!E:E) -> 142514.73
A4: Current Value | B4: =SUM(IND_HOLDINGS!G:G) -> 164171.72 | D4: 💰Biggest Profit | E4: =INDEX(IND_HOLDINGS!A2:A20, MATCH(MAX(IND_HOLDINGS!I2:I20), IND_HOLDINGS!I2:I20, 0)) -> Nippon India Silver ETF | F4: =MAX(IND_HOLDINGS!I2:I20) -> 10500.8
A5: Total Profit | B5: =SUM(IND_HOLDINGS!I:I) -> 21656.99
A6: Portfolio Return | B6: =SUM(IND_HOLDINGS!I:I)/SUM(IND_HOLDINGS!E:E) -> 0.15196317 | D6: 📉Worst Performer | E6: =INDEX(IND_HOLDINGS!A2:A20, MATCH(MIN(IND_HOLDINGS!I2:I20), IND_HOLDINGS!I2:I20, 0)) -> Suzlon Energy Ltd | F6: =MIN(IND_HOLDINGS!I2:I20) -> -233.48
A7: CAGR | B7: =(B4/B3)-1 -> 0.15196317
A8: Total Assets | B8: =COUNTA(IND_HOLDINGS!A2:A100) -> 9

Sheet PORT_HISTORY
A1: Date | B1: Invested | C1: Portfolio Value | D1: Profit | E1: Return %
A2: 45902 | B2: 83 | C2: 83 | D2: =C2-B2 -> 0 | E2: =IF(B2=0,"",D2/B2) -> 0
A3: 45923 | B3: 1073 | C3: 1090 | D3: =C3-B3 -> 17 | E3: =IF(B3=0,"",D3/B3) -> 0.01584343
A4: 45976 | B4: 1456 | C4: 1500 | D4: =C4-B4 -> 44 | E4: =IF(B4=0,"",D4/B4) -> 0.03021978
A5: 46003 | B5: 1291 | C5: 1700 | D5: =C5-B5 -> 409 | E5: =IF(B5=0,"",D5/B5) -> 0.31680868
A6: 46005 | B6: 21958 | C6: 23000 | D6: =C6-B6 -> 1042 | E6: =IF(B6=0,"",D6/B6) -> 0.047454231
A7: 46008 | B7: 22697 | C7: 24000 | D7: =C7-B7 -> 1303 | E7: =IF(B7=0,"",D7/B7) -> 0.057408468
A8: 46020 | B8: 142515 | C8: 145000 | D8: =C8-B8 -> 2485 | E8: =IF(B8=0,"",D8/B8) -> 0.017436761
A9: 46037 | B9: 142515 | C9: 150500 | D9: =C9-B9 -> 7985 | E9: =IF(B9=0,"",D9/B9) -> 0.05602919
A10: 46054 | B10: 142515 | C10: 154800 | D10: =C10-B10 -> 12285 | E10: =IF(B10=0,"",D10/B10) -> 0.086201452
A11: 46073 | B11: 142515 | C11: 158200 | D11: =C11-B11 -> 15685 | E11: =IF(B11=0,"",D11/B11) -> 0.11005859
A12: 46088 | B12: 142515 | C12: 161355 | D12: =C12-B12 -> 18840 | E12: =IF(B12=0,"",D12/B12) -> 0.13219661
E13: =IFERROR(D13/B13,"")
E14: =IFERROR(D14/B14,"")
E15: =IFERROR(D15/B15,"")

Sheet SIP
A1: Date | B1: NAME | C1: BUY/Sell | D1: Units | E1: NAV
A2: 45295 | B2: KOTAK LARGE CAP FUND | C2: BUY | D2: 0.891 | E2: 561.063
A3: 45295 | B3: NIPPON INDIA LARGE CAP FUND | C3: BUY | D3: 5.737 | E3: 87.1447
A4: 45569 | B4: KOTAK LARGE CAP FUND | C4: BUY | D4: 0.877 | E4: 569.943
A5: 45569 | B5: NIPPON INDIA LARGE CAP FUND | C5: BUY | D5: 5.64 | E5: 88.6487
A6: 13/05/2024 | B6: KOTAK LARGE CAP FUND | C6: BUY | D6: 0.887 | E6: 563.586
A7: 13/05/2024 | B7: NIPPON INDIA LARGE CAP FUND | C7: BUY | D7: 5.735 | E7: 87.174
A8: 45633 | B8: KOTAK LARGE CAP FUND | C8: BUY | D8: 0.787 | E8: 635.358
A9: 45633 | B9: NIPPON INDIA LARGE CAP FUND | C9: BUY | D9: 5.134 | E9: 97.3785
A10: 28/08/2024 | B10: KOTAK LARGE CAP FUND | C10: BUY | D10: 0.769 | E10: 649.826
A11: 28/08/2024 | B11: NIPPON INDIA LARGE CAP FUND | C11: BUY | D11: 5.062 | E11: 98.7789
A12: 23/09/2024 | B12: KOTAK LARGE CAP FUND | C12: BUY | D12: 0.742 | E12: 673.773
A13: 23/09/2024 | B13: NIPPON INDIA LARGE CAP FUND | C13: BUY | D13: 4.919 | E13: 101.6433
A14: 28/10/2024 | B14: KOTAK LARGE CAP FUND | C14: BUY | D14: 0.792 | E14: 631.235
A15: 28/10/2024 | B15: NIPPON INDIA LARGE CAP FUND | C15: BUY | D15: 5.207 | E15: 96.0172
A16: 25/11/2024 | B16: KOTAK LARGE CAP FUND | C16: BUY | D16: 0.789 | E16: 633.369
A17: 25/11/2024 | B17: NIPPON INDIA LARGE CAP FUND | C17: BUY | D17: 5.161 | E17: 96.8798
A18: 26/12/2024 | B18: KOTAK LARGE CAP FUND | C18: BUY | D18: 0.796 | E18: 628.367
A19: 26/12/2024 | B19: NIPPON INDIA LARGE CAP FUND | C19: BUY | D19: 5.198 | E19: 96.1901
A20: 28/01/2025 | B20: KOTAK LARGE CAP FUND | C20: BUY | D20: 0.842 | E20: 594.02
A21: 28/01/2025 | B21: NIPPON INDIA LARGE CAP FUND | C21: BUY | D21: 5.542 | E21: 90.2227
... A25: 25/04/2025 | B25: NIPPON INDIA LARGE CAP FUND | C25: BUY | D25: 4.742 | E25: 94.8844
A26: 45694 | B26: KOTAK LARGE CAP FUND | C26: BUY | D26: 0.774 | E26: 645.759
A27: 45694 | B27: NIPPON INDIA LARGE CAP FUND | C27: BUY | D27: 5.036 | E27: 99.2736
A28: 45664 | B28: KOTAK LARGE CAP FUND | C28: BUY | D28: 0.45 | E28: 666.789
A29: 45664 | B29: NIPPON INDIA LARGE CAP FUND | C29: BUY | D29: 2.933 | E29: 102.2738
A30: 24/07/2025 | B30: KOTAK LARGE CAP FUND | C30: BUY | D30: 0.759 | E30: 658.465
A31: 24/07/2025 | B31: NIPPON INDIA LARGE CAP FUND | C31: BUY | D31: 4.934 | E31: 101.3281
A32: 25/08/2025 | B32: KOTAK LARGE CAP FUND | C32: BUY | D32: 0.757 | E32: 660.068
A33: 25/08/2025 | B33: NIPPON INDIA LARGE CAP FUND | C33: BUY | D33: 4.886 | E33: 102.3387
A34: 26/09/2025 | B34: KOTAK LARGE CAP FUND | C34: BUY | D34: 0.843 | E34: 652.649
A35: 26/09/2025 | B35: NIPPON INDIA LARGE CAP FUND | C35: BUY | D35: 5.428 | E35: 101.3125
A36: 27/10/2025 | B36: KOTAK LARGE CAP FUND | C36: BUY | D36: 0.804 | E36: 684.165
A37: 27/10/2025 | B37: NIPPON INDIA LARGE CAP FUND | C37: BUY | D37: 5.228 | E37: 105.1974
A38: 26/11/2025 | B38: KOTAK LARGE CAP FUND | C38: BUY | D38: 0.797 | E38: 690.074
A39: 26/11/2025 | B39: NIPPON INDIA LARGE CAP FUND | C39: BUY | D39: 5.209 | E39: 105.5755
B40: NIPPON INDIA LARGE CAP FUND | C40: BUY
B41: Nippon India Mid Cap Fund | C41: BUY

Sheet SIP-SUMMARY
A1: Fund Name | B1: Scheme Code | C1: Current NAV | D1: Total Units | E1: Avg NAV | F1: Invested | G1: Current Value | H1: P/L | I1: P/L %
A2: {=_xlfn.UNIQUE(_xlfn._xlws.FILTER(SIP!B2:B100,SIP!B2:B100<>""))} -> KOTAK LARGE CAP FUND | B2: - | C2: 643 | D2: =SUMIF(SIP!B:B,A2,SIP!D:D) -> 14.94 | E2: =IFERROR(F2/D2,0) -> 629.09063 | F2: {=SUMPRODUCT((SIP!B2:B100=A2)*(SIP!D2:D100)*(SIP!E2:E100))} -> 9398.614 | G2: =D2*C2 -> 9606.42 | H2: =IFERROR(G2-F2,0) -> 207.80602 | I2: =IFERROR(H2/F2,0) -> 0.022110284
A3: NIPPON INDIA LARGE CAP FUND | B3: - | C3: 98 | D3: =SUMIF(SIP!B:B,A3,SIP!D:D) -> 97.364 | E3: =IFERROR(F3/D3,0) -> 96.539194 | F3: {=SUMPRODUCT((SIP!B3:B101=A3)*(SIP!D3:D101)*(SIP!E3:E101))} -> 9399.4421 | G3: =D3*C3 -> 9541.672 | H3: =IFERROR(G3-F3,0) -> 142.22995 | I3: =IFERROR(H3/F3,0) -> 0.015131744
A4: Nippon India Mid Cap Fund | B4: - | D4: =SUMIF(SIP!B:B,A4,SIP!D:D) -> 0 | E4: =IFERROR(F4/D4,0) -> 0 | F4: {=SUMPRODUCT((SIP!B4:B102=A4)*(SIP!D4:D102)*(SIP!E4:E102))} -> 0 | G4: =D4*C4 -> 0 | H4: =IFERROR(G4-F4,0) -> 0 | I4: =IFERROR(H4/F4,0) -> 0

Sheet FORMULA_REFERENCE
